ostatslib/__init__.py
ostatslib/actions/__init__.py
ostatslib/actions/action.py
ostatslib/actions/actions_space.py
ostatslib/actions/classifiers/__init__.py
ostatslib/actions/classifiers/decision_tree.py
ostatslib/actions/classifiers/linear_support_vector_classification.py
ostatslib/actions/classifiers/logistic_regression.py
ostatslib/actions/classifiers/random_forest.py
ostatslib/actions/classifiers/support_vector_classification.py
ostatslib/actions/clustering/__init__.py
ostatslib/actions/clustering/dbscan.py
ostatslib/actions/clustering/k_means.py
ostatslib/actions/exploratory_actions/__init__.py
ostatslib/actions/exploratory_actions/_get_exploratory_reward.py
ostatslib/actions/exploratory_actions/get_log_rows_count.py
ostatslib/actions/exploratory_actions/get_response_unique_values_ratio.py
ostatslib/actions/exploratory_actions/infer_response_dtype.py
ostatslib/actions/exploratory_actions/is_response_dichotomous_check.py
ostatslib/actions/exploratory_actions/is_response_discrete_check.py
ostatslib/actions/exploratory_actions/is_response_positive_values_only_check.py
ostatslib/actions/exploratory_actions/is_response_quantitative_check.py
ostatslib/actions/exploratory_actions/time_convertible_variable_search.py
ostatslib/actions/regression_models/__init__.py
ostatslib/actions/regression_models/decision_tree_regression.py
ostatslib/actions/regression_models/linear_regression.py
ostatslib/actions/regression_models/linear_support_vector_regression.py
ostatslib/actions/regression_models/poisson_regression.py
ostatslib/actions/regression_models/random_forest_regression.py
ostatslib/actions/regression_models/support_vector_regression.py
ostatslib/actions/regression_models/time_series_auto_arima.py
ostatslib/actions/utils/__init__.py
ostatslib/actions/utils/calculate_score_reward.py
ostatslib/actions/utils/explainability_rewards.py
ostatslib/actions/utils/model_selection.py
ostatslib/actions/utils/reward_cap.py
ostatslib-0.5.1.dist-info/LICENSE
ostatslib-0.5.1.dist-info/METADATA
ostatslib-0.5.1.dist-info/WHEEL
ostatslib-0.5.1.dist-info/RECORD
