Metadata-Version: 2.1
Name: ostatslib
Version: 0.5.1
Summary: Open Statistical Analysis Agent Library
Home-page: https://github.com/OStatsAA/ostatslib
License: MIT
Author: Guilherme
Author-email: g.lisboa.oliveira@outlook.com
Requires-Python: >=3.11,<3.12
Classifier: License :: OSI Approved :: MIT License
Classifier: Programming Language :: Python :: 3
Classifier: Programming Language :: Python :: 3.11
Requires-Dist: datacooker (>=0.4.1,<0.5.0)
Requires-Dist: kneed (>=0.8.3,<0.9.0)
Requires-Dist: numpy (>=1.23.4,<2.0.0)
Requires-Dist: pandas (>=2.0.1,<3.0.0)
Requires-Dist: pmdarima (>=2.0.2,<3.0.0)
Requires-Dist: pmlb (>=1.0.1.post3,<2.0.0)
Requires-Dist: scikit-learn (>=1.1.2,<2.0.0)
Requires-Dist: scipy (>=1.9.3,<2.0.0)
Requires-Dist: stable-baselines3 (==2.0.0a10)
Requires-Dist: statsmodels (>=0.13.2,<0.15.0)
Requires-Dist: tabulate (>=0.9.0,<0.10.0)
Requires-Dist: tensorboard (>=2.12.0,<3.0.0)
Project-URL: Repository, https://github.com/OStatsAA/ostatslib
